skyramp/__init__.py
skyramp/async_test_status.py
skyramp/client.py
skyramp/client_base.py
skyramp/deprecated_status.py
skyramp/docker_client.py
skyramp/endpoint.py
skyramp/endpoint_base.py
skyramp/k8s_client.py
skyramp/local_client.py
skyramp/mock.py
skyramp/mock_description.py
skyramp/mock_object.py
skyramp/mock_v2.py
skyramp/response.py
skyramp/rest_param.py
skyramp/robot_listener.py
skyramp/robot_listener_v1.py
skyramp/robot_test_suite.py
skyramp/scenario.py
skyramp/scenario_v2.py
skyramp/service.py
skyramp/smart_playwright.py
skyramp/test.py
skyramp/test_assert.py
skyramp/test_description.py
skyramp/test_helper.py
skyramp/test_load_config.py
skyramp/test_pattern.py
skyramp/test_request.py
skyramp/test_request2.py
skyramp/test_response2.py
skyramp/test_status.py
skyramp/test_status_interactive_mode.py
skyramp/traffic_config.py
skyramp/user_credential.py
skyramp/utils.py
skyramp/lib/skyramp-darwin-amd64.dylib
skyramp/lib/skyramp-darwin-amd64.h
skyramp/lib/skyramp-darwin-arm64.dylib
skyramp/lib/skyramp-darwin-arm64.h
skyramp/lib/skyramp-linux-386.h
skyramp/lib/skyramp-linux-386.so
skyramp/lib/skyramp-linux-amd64.h
skyramp/lib/skyramp-linux-amd64.so
skyramp/lib/skyramp-windows-amd64.dll
skyramp/lib/skyramp-windows-amd64.h
skyramp-1.3.5.dist-info/licenses/LICENSE
skyramp-1.3.5.dist-info/WHEEL
skyramp-1.3.5.dist-info/METADATA
skyramp-1.3.5.dist-info/RECORD
