Metadata-Version: 2.4
Name: skyramp
Version: 1.3.5
Summary: module for leveraging skyramp cli functionality
Requires-Python: >=3.0
Classifier: License :: OSI Approved :: MIT License
License-File: LICENSE
Requires-Dist: pyyaml >=6.0.2
Requires-Dist: typing_extensions >= 4.9.0
Requires-Dist: robotframework >= 4.1.2, <7.4
Requires-Dist: playwright >= 1.55
